gstin_generator/__init__.py
gstin_generator/_internal.py
gstin_generator/core.py
gstin_generator/version.py
random_gstin_generator-0.1.4.dist-info/METADATA
random_gstin_generator-0.1.4.dist-info/WHEEL
random_gstin_generator-0.1.4.dist-info/RECORD
