Metadata-Version: 2.3
Name: random-gstin-generator
Version: 0.1.4
Summary: Creates random India GSTIN numbers that pass validation. For testing purposes only.
Author: Mohammed Saleel
Author-email: mohammed.saleel0099@gmail.com
Requires-Python: >=3.8
Classifier: Programming Language :: Python :: 3
Classifier: Programming Language :: Python :: 3.8
Classifier: Programming Language :: Python :: 3.9
Classifier: Programming Language :: Python :: 3.10
Classifier: Programming Language :: Python :: 3.11
Classifier: Programming Language :: Python :: 3.12
Classifier: Programming Language :: Python :: 3.13
